LICENSE
treesync/__init__.py
treesync/bin/__init__.py
treesync/bin/treesync/__init__.py
treesync/bin/treesync/commands/__init__.py
treesync/bin/treesync/commands/base.py
treesync/bin/treesync/commands/list.py
treesync/bin/treesync/commands/pull.py
treesync/bin/treesync/commands/push.py
treesync/bin/treesync/commands/show.py
treesync/bin/treesync/main.py
treesync/configuration/__init__.py
treesync/configuration/defaults.py
treesync/configuration/hosts.py
treesync/configuration/loader.py
treesync/configuration/servers.py
treesync/configuration/sources.py
treesync/configuration/targets.py
treesync/constants.py
treesync/exceptions.py
treesync/host.py
treesync/target.py
treesync-1.5.1.dist-info/LICENSE
treesync-1.5.1.dist-info/METADATA
treesync-1.5.1.dist-info/WHEEL
treesync-1.5.1.dist-info/entry_points.txt
treesync-1.5.1.dist-info/RECORD
